MANIFEST.in
Makefile
README.rst
setup.py
oredis/__init__.py
oredis/exceptions.py
oredis/fields.py
oredis/manager.py
oredis/models.py
oredis/utils.py
oredis.egg-info/PKG-INFO
oredis.egg-info/SOURCES.txt
oredis.egg-info/dependency_links.txt
oredis.egg-info/requires.txt
oredis.egg-info/top_level.txt