Metadata-Version: 1.0
Name: oredis
Version: 0.1
Summary: Object-hash mapping library for Redis
Home-page: http://github.com/lispython/oredis/
Author: Alexandr
Author-email: alex@obout.ru
License: BSD
Keywords: Object,hash mapping,redis
Platform: any
Classifier: Development Status :: 4 - Beta
Classifier: Environment :: Console
Classifier: Intended Audience :: Developers
Classifier: License :: OSI Approved :: MIT License
Classifier: Operating System :: OS Independent
Classifier: Programming Language :: Python
